aioraft/VERSION
aioraft/__init__.py
aioraft/client.py
aioraft/protocol.py
aioraft/raft.py
aioraft/server.py
aioraft/types.py
aioraft/utils.py
aioraft/protos/raft_pb2.py
aioraft/protos/raft_pb2_grpc.py
aioraft_ng-0.1.5.dist-info/LICENSE
aioraft_ng-0.1.5.dist-info/METADATA
aioraft_ng-0.1.5.dist-info/WHEEL
aioraft_ng-0.1.5.dist-info/top_level.txt
aioraft_ng-0.1.5.dist-info/RECORD
