Metadata-Version: 2.1
Name: aioraft-ng
Version: 0.1.5
Summary: An implementation of `Raft` consensus algorithm written in asyncio-based Python 3.
Home-page: https://github.com/lablup/aioraft-ng
Author: Lablup Inc.
Maintainer: rapsealk
Maintainer-email: jskang@lablup.com
License: Apache License 2.0
Requires-Python: >=3.10
License-File: LICENSE
Requires-Dist: grpcio (==1.48.2)
Requires-Dist: protobuf (==3.19.4)
Requires-Dist: tomli (~=2.0.1)
Provides-Extra: dev
Requires-Dist: black ; extra == 'dev'
Requires-Dist: flake8 ; extra == 'dev'
Requires-Dist: grpcio-tools (==1.48.2) ; extra == 'dev'
Requires-Dist: isort ; extra == 'dev'
Requires-Dist: mypy ; extra == 'dev'
Requires-Dist: pytest (~=7.1.2) ; extra == 'dev'
Requires-Dist: pytest-asyncio (~=0.19.0) ; extra == 'dev'
Requires-Dist: types-protobuf ; extra == 'dev'
